pass_cli/__init__.py
pass_cli/__main__.py
pass_cli/enums.py
pass_cli/utils.py
pass_cli/data/pass_cli.ini.skel
pass_cli/ui_parts/__init__.py
pass_cli/ui_parts/boxes.py
pass_cli/ui_parts/buttons.py
pass_cli-0.0.6.dist-info/licenses/AUTHORS
pass_cli-0.0.6.dist-info/licenses/LICENSE
pass_cli-0.0.6.dist-info/METADATA
pass_cli-0.0.6.dist-info/WHEEL
pass_cli-0.0.6.dist-info/entry_points.txt
pass_cli-0.0.6.dist-info/top_level.txt
pass_cli-0.0.6.dist-info/RECORD
