Metadata-Version: 2.4
Name: pass_cli
Version: 0.0.6
Summary: CLI interface for pass
Home-page: https://github.com/a7f4/pass_cli
Author: Aleksandr Block
Author-email: aleksandr.block@gmail.com
License: MIT
Keywords: pass_cli
Platform: any
Classifier: Development Status :: 3 - Alpha
Classifier: Programming Language :: Python :: 3
Classifier: License :: OSI Approved :: MIT License
Classifier: Operating System :: Unix
License-File: LICENSE
License-File: AUTHORS
Requires-Dist: pyperclip==1.7.0
Requires-Dist: urwid==2.0.1
Requires-Dist: configparser; python_version == "3.5"
Dynamic: author
Dynamic: author-email
Dynamic: classifier
Dynamic: description
Dynamic: description-content-type
Dynamic: home-page
Dynamic: keywords
Dynamic: license
Dynamic: license-file
Dynamic: platform
Dynamic: provides-extra
Dynamic: requires-dist
Dynamic: summary
